dyndis/__init__.py
dyndis/_version.py
dyndis/annotation_filter.py
dyndis/exceptions.py
dyndis/implementor.py
dyndis/multidispatch.py
dyndis/topological_sort.py
dyndis/weaktupledict.py
dyndis-0.2.0.dist-info/LICENSE
dyndis-0.2.0.dist-info/WHEEL
dyndis-0.2.0.dist-info/METADATA
dyndis-0.2.0.dist-info/RECORD
