Metadata-Version: 2.1
Name: dyndis
Version: 0.2.0
Summary: 
Home-page: https://github.com/bentheiii/dyndis
License: MIT
Author: ben avrahami
Author-email: dontcallme@illcall.you
Requires-Python: >=3.7,<4.0
Classifier: License :: OSI Approved :: MIT License
Classifier: Programming Language :: Python :: 3
Classifier: Programming Language :: Python :: 3.7
Classifier: Programming Language :: Python :: 3.8
Classifier: Programming Language :: Python :: 3.9
Requires-Dist: sortedcontainers
Project-URL: Repository, https://github.com/bentheiii/dyndis
